LICENSE
MANIFEST.in
README.rst
main.py
setup.cfg
setup.py
xytool/__init__.py
xytool/__main__.py
xytool/api.py
xytool/config.ini
xytool/config.py
xytool.egg-info/PKG-INFO
xytool.egg-info/SOURCES.txt
xytool.egg-info/dependency_links.txt
xytool.egg-info/entry_points.txt
xytool.egg-info/requires.txt
xytool.egg-info/top_level.txt
xytool/common/__init__.py
xytool/common/common.py
xytool/common/extension.py
xytool/common/file.py
xytool/common/globalvar.py
xytool/common/interaction.py
xytool/common/mail.py
xytool/common/sysenv.py
xytool/common/threadpool.py
xytool/common/timeusage.py
xytool/common/useragent.py
xytool/common/xylog.py
xytool/db/__init__.py
xytool/db/database_block.py
xytool/db/dbmanager.py
xytool/ios/CommonScript.py
xytool/ios/__init__.py
xytool/ios/cert.py
xytool/ios/gitandjira.py
xytool/ios/iosProjectTool.py
xytool/ios/oclint.py
xytool/ios/package.py
xytool/ip/DataStore.py
xytool/ip/HtmlDownloader.py
xytool/ip/HtmlPraser.py
xytool/ip/IPAddress.py
xytool/ip/ISqlHelper.py
xytool/ip/MongoHelper.py
xytool/ip/ProxyCrawl.py
xytool/ip/RedisHelper.py
xytool/ip/SqlHelper.py
xytool/ip/Validator.py
xytool/ip/__init__.py
xytool/ip/compatibility.py
xytool/ip/config.py
xytool/ip/exception.py
xytool/ip/ipmanager.py
xytool/packagePB/__init__.py
xytool/packagePB/package.py
xytool/scripts/__init__.py
xytool/scripts/xytool.py
xytool/source/__init__.py
xytool/source/html.py
xytool/source/image.py
xytool/source/htmlx/__init__.py
xytool/source/htmlx/html2pt.py
xytool/source/img/__init__.py
xytool/source/img/pic2py.py
xytool/test/__init__.py
xytool/test/test.py
xytool/test/test1234.py
xytool/test/testUI.py
xytool/test/testtool.py
xytool/tool/__init__.py
xytool/tool/pictoannotation.py